fi_fsa_v3/__init__.py
fi_fsa_v3/__init__.pyi
fi_fsa_v3/fi_fsa_v3.cp312-win_amd64.pyd
fi_fsa_v3/fsav3.dll
fi_fsa_v3/msvcp140.dll
fi_fsa_v3/vcruntime140.dll
fi_fsa_v3/vcruntime140_1.dll
fi_fsa_v3-0.0.15.dist-info/METADATA
fi_fsa_v3-0.0.15.dist-info/WHEEL
fi_fsa_v3-0.0.15.dist-info/top_level.txt
fi_fsa_v3-0.0.15.dist-info/RECORD
