Metadata-Version: 2.4
Name: fi_fsa_v3
Version: 0.0.15
Summary: Fourier Intelligence Actuator V3 SDK for Python.
Author: Honglu Wang
Author-email: honglu.wang@fftai.com
License: MIT
Dynamic: author
Dynamic: author-email
Dynamic: license
Dynamic: summary
